fact/__init__.py
fact/cli.py
fact/lib.py
fact/py.typed
mlfact-1.0.2.dist-info/LICENSE.txt
mlfact-1.0.2.dist-info/METADATA
mlfact-1.0.2.dist-info/WHEEL
mlfact-1.0.2.dist-info/entry_points.txt
mlfact-1.0.2.dist-info/top_level.txt
mlfact-1.0.2.dist-info/RECORD
