Metadata-Version: 2.1
Name: mlfact
Version: 1.0.2
Summary: Example Python project
Home-page: https://github.com/xmarlem/python-blueprint
Author: 
License: MIT
Keywords: python
Platform: UNKNOWN
Classifier: Development Status :: 4 - Beta
Classifier: Intended Audience :: Developers
Classifier: License :: OSI Approved :: MIT License
Classifier: Programming Language :: Python
Classifier: Programming Language :: Python :: 3
Classifier: Programming Language :: Python :: 3 :: Only
Classifier: Programming Language :: Python :: 3.6
Classifier: Programming Language :: Python :: 3.7
Classifier: Programming Language :: Python :: 3.8
Requires-Python: >=3.6
Requires-Dist: colorama (==0.4.4)
Requires-Dist: exitstatus (==2.0.1)
